{"family": "Xyridaceae", "url": "https://www.philippineplants.org/Families/Xyridaceae.html", "references": [{"text": "Hansen, B. 1982. Addenda & Corridenda. Flora Malesiana series 1, 9: 571-573", "url": "http://www.biodiversitylibrary.org/item/91490#page/623/mode/1up"}, {"text": "Royen, P van. 1953. Xyridaceae. Flora Malesiana series 1, 4: 367-376", "url": "https://repository.naturalis.nl/pub/532607/FM1S1948004001061.pdf"}], "genera": [{"genus": "Xyris", "authors": "L.", "last_edited": "Last edited by Pieter B. Pelser & John Edward Matulina Villasis, 31 August 2024", "species": [{"u": 10725, "scientific_name": "Xyris capensis", "taxon_name": "Xyris capensis", "category": "", "status": "Native.", "citation": "Thunb. , Prodr. Pl. Cap. (1794) 12 ; Hansen, Fl. Males. ser. 1, 9 (1982) 573. = Xyris capensis var. schoenoides (Mart.) L.A.Nilsson , Öfvers. Kongl. Vetensk.-Akad. Förh. 24 (1892) 41 ; Royen, Fl. Males. ser. 1, 4 (1953) 374; ≡ Xyris schoenoides Mart. , Pl. Asiat. Rar. 3 (1832) 30.", "distribution": "Africa, America, China, India, Indochina, Malesia, Philippines, Thailand. LUZON: Benguet, MINDANAO: Bukidnon.", "notes": "Recorded in the Philippines from Mt Tabayoc (Jacobs 7436 and 7491) and Mt Limbawon (Fritsch et al. 2091), in open wet places among grasses and sphagnum, including mountain swamps and lake banks. 600-3300m.", "conservation_status": "Least Concern (IUCN 3.1).", "dao_category": "", "other_fields": {}, "gallery_url": "", "thumbs": [], "full": []}, {"u": 10726, "scientific_name": "Xyris complanata", "taxon_name": "Xyris complanata", "category": "", "status": "Native.", "citation": "R.Br. , Prodr. Fl. Nov. Holland. (1810) 256 ; Merrill, EPFP 1 (1923) 192; Royen, Fl. Males. ser. 1, 4 (1953) 369.", "distribution": "Australia, China, India, Indochina, Malesia, Sri Lanka, Thailand. LUZON: Bulacan, Isabela, SEMIRARA.", "notes": "In fields and moist sandy soil in coastal areas. 0-1600m.", "conservation_status": "Least Concern (IUCN 3.1).", "dao_category": "", "other_fields": {}, "gallery_url": "", "thumbs": [], "full": []}, {"u": 10727, "scientific_name": "Xyris indica", "taxon_name": "Xyris indica", "category": "", "status": "Native.", "citation": "L. , Sp. Pl., 1st Ed. (1753) 42 ; Royen, Fl. Males. ser. 1, 4 (1953) 373; B.Hansen, Fl. Males. ser. 1, 9 (1982) 572.", "distribution": "Australia, China, India, Malesia, Myanmar, Sri Lanka, Thailand.", "notes": "In wet grasslands and inundated rice fields. 0-250(-900)m.", "conservation_status": "Least Concern (IUCN 3.1).", "dao_category": "", "other_fields": {}, "gallery_url": "", "thumbs": [], "full": []}, {"u": 10728, "scientific_name": "Xyris pauciflora", "taxon_name": "Xyris pauciflora", "category": "", "status": "Native.", "citation": "Willd. , Phytographia (1794) 2 ; Merr., Fl. Manila (1912) 192; Merrill, EPFP 1 (1923) 192; Royen, Fl. Males. ser. 1, 4 (1953) 371.", "distribution": "Australia, China, Hong Kong, India, Indochina, Malesia, Myanmar, Sri Lanka, Taiwan, Thailand. LUZON: Bulacan, NCR, Rizal, Zambales, PANAY.", "notes": "In open wet places, swamps, and fields. 0-300(-900)m.", "conservation_status": "Least Concern (IUCN 3.1).", "dao_category": "", "other_fields": {}, "gallery_url": "", "thumbs": [], "full": []}]}]}